noogle_mcp_server/__init__.py
noogle_mcp_server/__main__.py
noogle_mcp_server/tools.py
noogle_mcp_server-0.1.0.dist-info/licenses/LICENSE
noogle_mcp_server-0.1.0.dist-info/METADATA
noogle_mcp_server-0.1.0.dist-info/WHEEL
noogle_mcp_server-0.1.0.dist-info/entry_points.txt
noogle_mcp_server-0.1.0.dist-info/top_level.txt
noogle_mcp_server-0.1.0.dist-info/RECORD
