Metadata-Version: 2.4
Name: noogle_mcp_server
Version: 0.1.0
Summary: A FastMCP server for querying Nix documentation from noogle.dev
Requires-Python: >=3.11
License-File: LICENSE
Requires-Dist: beautifulsoup4>=4.13.4
Requires-Dist: fastmcp
Requires-Dist: httpx
Provides-Extra: test
Requires-Dist: pytest>=8.4.1; extra == "test"
Requires-Dist: pytest-httpx>=0.35.0; extra == "test"
Requires-Dist: pytest-asyncio>=1.0.0; extra == "test"
Dynamic: license-file
